UTF8000/UTF8000Byte.py
UTF8000/UTF8000IncrementalDecoder.py
UTF8000/UTF8000Int.py
UTF8000/__init__.py
UTF_8000-1.0.0.dist-info/LICENSE
UTF_8000-1.0.0.dist-info/METADATA
UTF_8000-1.0.0.dist-info/WHEEL
UTF_8000-1.0.0.dist-info/top_level.txt
UTF_8000-1.0.0.dist-info/RECORD
