Metadata-Version: 2.1
Name: UTF-8000
Version: 1.0.0
Summary: Unlimited UTF-8!
License:                     GNU GENERAL PUBLIC LICENSE
Project-URL: Homepage, https://github.com/jb2170/UTF-8000/
License-File: LICENSE
